sqlean/__init__.py
sqlean/_sqlite3.cpython-313-x86_64-linux-gnu.so
sqlean/dbapi2.py
sqlean/extensions.py
sqlean_py-3.50.4.4.dist-info/METADATA
sqlean_py-3.50.4.4.dist-info/WHEEL
sqlean_py-3.50.4.4.dist-info/top_level.txt
sqlean_py-3.50.4.4.dist-info/RECORD
