Metadata-Version: 2.4
Name: sqlean.py
Version: 3.50.4.4
Summary: sqlite3 with extensions
Home-page: https://github.com/nalgeon/sqlean.py
Author: Anton Zhiyanov
Author-email: m@antonz.org
License: zlib/libpng
Platform: ALL
Classifier: Development Status :: 4 - Beta
Classifier: Intended Audience :: Developers
Classifier: Operating System :: MacOS :: MacOS X
Classifier: Operating System :: POSIX
Classifier: Programming Language :: C
Classifier: Programming Language :: Python
Classifier: Topic :: Database :: Database Engines/Servers
Classifier: Topic :: Software Development :: Libraries :: Python Modules
Requires-Python: >=3.9
Dynamic: author
Dynamic: author-email
Dynamic: classifier
Dynamic: description
Dynamic: description-content-type
Dynamic: home-page
Dynamic: license
Dynamic: platform
Dynamic: requires-python
Dynamic: summary
